package_eh/__init__.py
package_eh-0.9.0.1.dist-info/METADATA
package_eh-0.9.0.1.dist-info/WHEEL
package_eh-0.9.0.1.dist-info/top_level.txt
package_eh-0.9.0.1.dist-info/RECORD
