Metadata-Version: 2.1
Name: package-eh
Version: 0.9.0.1
Summary: Hello world enterprise edition
Home-page: UNKNOWN
Author: eh
Author-email: eh@prism39.com
License: UNKNOWN
Keywords: pip,eh,example
Platform: UNKNOWN
